[{"9": [-Infinity, -0.408477], "2": [0.0, Infinity], "11": [-Infinity, -1.0], "8": [0.0, Infinity], "label": 0}, {"11": [0.0, Infinity], "2": [-Infinity, 1.0], "label": 0}, {"11": [0.0, Infinity], "7": [-Infinity, 173.0], "9": [0.885408, Infinity], "label": 0}, {"2": [-Infinity, 0.0], "11": [-1.0, Infinity], "8": [0.0, Infinity], "9": [-0.408477, Infinity], "label": 0}, {"9": [-Infinity, -0.408477], "11": [-Infinity, -1.0], "8": [0.0, Infinity], "2": [-Infinity, 0.0], "label": 0}, {"9": [0.767215, Infinity], "2": [-Infinity, 0.0], "label": 0}, {"7": [173.0, Infinity], "1": [-Infinity, 0.0], "9": [-Infinity, 1.262019], "0": [56.0, Infinity], "label": 1}, {"9": [-Infinity, 0.971613], "12": [-Infinity, 1.0], "3": [-Infinity, 134.0], "7": [145.0, Infinity], "0": [58.0, Infinity], "10": [1.0, Infinity], "label": 1}, {"9": [-Infinity, 1.9], "2": [0.0, Infinity], "label": 1}, {"2": [1.0, Infinity], "label": 1}]